ca_alerts_client/__init__.py
ca_alerts_client/abs_channel.py
ca_alerts_client/channel.py
ca_alerts_client/exceptions.py
ca_alerts_client/helpers.py
ca_alerts_client-0.2.dist-info/METADATA
ca_alerts_client-0.2.dist-info/WHEEL
ca_alerts_client-0.2.dist-info/top_level.txt
ca_alerts_client-0.2.dist-info/RECORD
