Metadata-Version: 2.1
Name: ca-alerts-client
Version: 0.2
Requires-Python: >=3.8
Requires-Dist: pandas ~=2.0.3
Requires-Dist: dataframe-image ~=0.2.4
Requires-Dist: tenacity ~=9.0.0
Requires-Dist: lxml ~=5.3.0
Requires-Dist: openpyxl ~=3.1.5
Requires-Dist: setuptools ~=72.1.0
Requires-Dist: pika ~=1.3.2
Requires-Dist: matplotlib ~=3.7.5
